audian/__init__.py
audian/analyzer.py
audian/audian.py
audian/buffereddata.py
audian/bufferedenvelope.py
audian/bufferedfilter.py
audian/bufferedspectrogram.py
audian/data.py
audian/databrowser.py
audian/fulltraceplot.py
audian/markerdata.py
audian/panels.py
audian/plotranges.py
audian/plugins.py
audian/rangeplot.py
audian/selectviewbox.py
audian/specitem.py
audian/spectrogramplot.py
audian/statisticsanalyzer.py
audian/timeaxisitem.py
audian/timeplot.py
audian/traceitem.py
audian/version.py
audian/yaxisitem.py
audian-2.4.dist-info/licenses/LICENSE
audian-2.4.dist-info/METADATA
audian-2.4.dist-info/WHEEL
audian-2.4.dist-info/entry_points.txt
audian-2.4.dist-info/top_level.txt
audian-2.4.dist-info/RECORD
