Metadata-Version: 2.4
Name: audian
Version: 2.4
Summary: GUI for viewing and analyzing recordings of animal vocalizations.
Author-email: Jan Benda <jan.benda@uni-tuebingen.de>
Maintainer-email: Jan Benda <jan.benda@uni-tuebingen.de>
License:                     GNU GENERAL PUBLIC LICENSE
Project-URL: Repository, https://github.com/bendalab/audian
Classifier: Development Status :: 4 - Beta
Classifier: Environment :: Console
Classifier: Intended Audience :: Science/Research
Classifier: License :: OSI Approved :: GNU General Public License v3 (GPLv3)
Classifier: Natural Language :: English
Classifier: Programming Language :: Python :: 3
Classifier: Programming Language :: Python :: 3.8
Classifier: Programming Language :: Python :: 3.12
Classifier: Operating System :: OS Independent
Classifier: Topic :: Multimedia :: Sound/Audio
Classifier: Topic :: Multimedia :: Sound/Audio :: Analysis
Classifier: Topic :: Scientific/Engineering
Classifier: Topic :: Software Development :: Libraries :: Python Modules
Requires-Python: >=3.8
License-File: LICENSE
Requires-Dist: scipy
Requires-Dist: numpy
Requires-Dist: numba
Requires-Dist: pandas
Requires-Dist: matplotlib
Requires-Dist: platformdirs
Requires-Dist: PyQt5
Requires-Dist: pyqtgraph
Requires-Dist: SoundFile
Requires-Dist: sounddevice
Requires-Dist: thunderlab>=1.6.0
Dynamic: license-file
